setup.py
common_bidso/__init__.py
common_bidso.egg-info/PKG-INFO
common_bidso.egg-info/SOURCES.txt
common_bidso.egg-info/dependency_links.txt
common_bidso.egg-info/requires.txt
common_bidso.egg-info/top_level.txt
common_bidso/data/__init__.py
common_bidso/decorators/__init__.py
common_bidso/decorators/jwt.py
common_bidso/helpers/__init__.py
common_bidso/helpers/logging.py
common_bidso/utils/__init__.py
common_bidso/utils/datetime.py
common_bidso/utils/phone_number.py
common_bidso/utils/request_utils.py
common_bidso/views/__init__.py
common_bidso/views/base_view.py